{
  "assets": {
    "clip-472a2445cce341c38026241af2567a6c6b74eb899f69d98a68f5845cb03afddf": {
      "bytes": 373775,
      "media_type": "video/webm",
      "path": "media/472a2445cce341c38026241af2567a6c6b74eb899f69d98a68f5845cb03afddf.webm",
      "sha256": "472a2445cce341c38026241af2567a6c6b74eb899f69d98a68f5845cb03afddf"
    },
    "clip-d857cbf8f0139347375a59e437e430505ab8ae19c27cb288ffadacdb6c7f827a": {
      "bytes": 44815,
      "media_type": "video/webm",
      "path": "media/d857cbf8f0139347375a59e437e430505ab8ae19c27cb288ffadacdb6c7f827a.webm",
      "sha256": "d857cbf8f0139347375a59e437e430505ab8ae19c27cb288ffadacdb6c7f827a"
    },
    "state-00f01e21acf6158b0f01569141e555690fb9ee56c78f6a68609dcd85a54aede0": {
      "bytes": 60,
      "media_type": "image/webp",
      "path": "media/45386cc70e17d73a9cabfe193842500a7f2ef153841e91f94b3d878546b3901a.webp",
      "sha256": "45386cc70e17d73a9cabfe193842500a7f2ef153841e91f94b3d878546b3901a"
    },
    "state-1470b435db147f0ad34d41366736506490dca88c6c815a77e60e925a0a986200": {
      "bytes": 5002,
      "media_type": "image/webp",
      "path": "media/89080347c053bf4a04ddb8f6b66c3c87896055509270adbd1bf789f9ed575c96.webp",
      "sha256": "89080347c053bf4a04ddb8f6b66c3c87896055509270adbd1bf789f9ed575c96"
    },
    "state-47cfc61413b27da988e80c74cf397de8af67114d2582a56ef6851edb1c6f7e86": {
      "bytes": 7990,
      "media_type": "image/webp",
      "path": "media/bbded3504c798f5af50d89a4aee36235c027dca09b9eb5d7344951fce87b9d41.webp",
      "sha256": "bbded3504c798f5af50d89a4aee36235c027dca09b9eb5d7344951fce87b9d41"
    },
    "state-c2629d271acf589fd50eb95bfce5d8491811f30f32d9c33baa275461488ce941": {
      "bytes": 16240,
      "media_type": "image/webp",
      "path": "media/d462e9f05854fa5261101417b7651a31df3ab345a6884ba5ff484a77ce18b090.webp",
      "sha256": "d462e9f05854fa5261101417b7651a31df3ab345a6884ba5ff484a77ce18b090"
    }
  },
  "audio": {
    "intervals": [
      {
        "presentation_end_ms": 9168,
        "presentation_start_ms": 0,
        "source_end_ms": 9168,
        "source_start_ms": 0
      },
      {
        "presentation_end_ms": 13416,
        "presentation_start_ms": 9168,
        "source_end_ms": 13416,
        "source_start_ms": 9168
      },
      {
        "presentation_end_ms": 18478,
        "presentation_start_ms": 13416,
        "source_end_ms": 18478,
        "source_start_ms": 13416
      },
      {
        "presentation_end_ms": 28632,
        "presentation_start_ms": 18478,
        "source_end_ms": 28632,
        "source_start_ms": 18478
      },
      {
        "presentation_end_ms": 34634,
        "presentation_start_ms": 28632,
        "source_end_ms": 34634,
        "source_start_ms": 28632
      },
      {
        "presentation_end_ms": 54486,
        "presentation_start_ms": 41334,
        "source_end_ms": 47786,
        "source_start_ms": 34634
      },
      {
        "presentation_end_ms": 65345,
        "presentation_start_ms": 54486,
        "source_end_ms": 58645,
        "source_start_ms": 47786
      },
      {
        "presentation_end_ms": 68452,
        "presentation_start_ms": 65345,
        "source_end_ms": 61752,
        "source_start_ms": 58645
      }
    ],
    "metadata": "audio.json"
  },
  "beats": [
    {
      "duration_ms": 13416,
      "guide": {
        "success_hint": "Install OmegaFlow in your project's Python environment."
      },
      "heading": "Install OmegaFlow",
      "id": "install",
      "offset_ms": 0,
      "payload": "beats/install.cast",
      "renderer": "terminal",
      "transition_in": null
    },
    {
      "duration_ms": 15216,
      "guide": {
        "success_hint": "Inspect and commit the generated recording workspace."
      },
      "heading": "Bootstrap Quickstart",
      "id": "bootstrap",
      "offset_ms": 13416,
      "payload": "beats/bootstrap.cast",
      "renderer": "terminal",
      "transition_in": null
    },
    {
      "duration_ms": 17378,
      "guide": {
        "success_hint": "The generated video is ready to play."
      },
      "heading": "Build The Video",
      "id": "build",
      "offset_ms": 28632,
      "payload": "beats/build.cast",
      "renderer": "terminal",
      "transition_in": null
    },
    {
      "duration_ms": 22442,
      "guide": {
        "success_hint": "The generated player is ready to publish with your docs."
      },
      "heading": "Play It In The Browser",
      "id": "play-in-browser",
      "offset_ms": 46010,
      "payload": "beats/play-in-browser.browser.json",
      "renderer": "browser",
      "transition_in": "window-open"
    }
  ],
  "manifest_version": 1,
  "presentation": {
    "browser": {
      "chrome": {
        "mode": "full"
      },
      "window": {
        "mode": "framed",
        "theme": "kde-breeze",
        "title": "OmegaFlow Player"
      }
    }
  },
  "recording": {
    "duration_ms": 68452,
    "id": "quickstart-demo",
    "title": "Quickstart Demo"
  },
  "renderers": {
    "browser": {
      "payload_version": 1
    },
    "terminal": {
      "payload_version": 1
    }
  }
}
